devtools_http_status/__init__.py
devtools_http_status-1.0.1.dist-info/METADATA
devtools_http_status-1.0.1.dist-info/WHEEL
devtools_http_status-1.0.1.dist-info/top_level.txt
devtools_http_status-1.0.1.dist-info/RECORD
