Metadata-Version: 2.1
Name: devtools_http_status
Version: 1.0.1
Summary: HTTP status code reference
Home-page: https://devtools.at/tools/http-status
Author: DevTools.at
Author-email: hello@devtools.at
Project-URL: Homepage, https://devtools.at/tools/http-status
Project-URL: Repository, https://github.com/devtools-at/http-status
Classifier: Development Status :: 4 - Beta
Classifier: Intended Audience :: Developers
Classifier: License :: OSI Approved :: MIT License
Classifier: Programming Language :: Python :: 3
Requires-Python: >=3.8
